orders_pr_contracts/__init__.py
orders_pr_contracts/auth.py
orders_pr_contracts/orders.py
orders_pr_contracts/users.py
orders_pr_contracts-0.2.0.dist-info/AUTHORS.rst
orders_pr_contracts-0.2.0.dist-info/LICENSE
orders_pr_contracts-0.2.0.dist-info/METADATA
orders_pr_contracts-0.2.0.dist-info/WHEEL
orders_pr_contracts-0.2.0.dist-info/top_level.txt
orders_pr_contracts-0.2.0.dist-info/RECORD
