Metadata-Version: 2.1
Name: orders-pr-contracts
Version: 0.2.0
Home-page: https://github.com/example/orders_pr_contracts
Author: contracts
Author-email: contracts@test.com
License: MIT license
Keywords: orders_pr_contracts
Classifier: Development Status :: 2 - Pre-Alpha
Classifier: Intended Audience :: Developers
Classifier: License :: OSI Approved :: MIT License
Classifier: Natural Language :: English
Classifier: Programming Language :: Python :: 3
Classifier: Programming Language :: Python :: 3.6
Classifier: Programming Language :: Python :: 3.7
Classifier: Programming Language :: Python :: 3.8
Requires-Python: >=3.6
License-File: LICENSE
License-File: AUTHORS.rst
Requires-Dist: pydantic
